migas/__init__.py
migas/_version.py
migas/config.py
migas/conftest.py
migas/helpers.py
migas/operations.py
migas/request.py
migas/utils.py
migas/error/__init__.py
migas/error/base.py
migas/error/nipype.py
migas/error/tests/test_error.py
migas/error/tests/test_nipype.py
migas/tests/__init__.py
migas/tests/conftest.py
migas/tests/test_config.py
migas/tests/test_operations.py
migas/tests/test_request.py
migas/tests/utils.py
migas-0.4.0.dist-info/METADATA
migas-0.4.0.dist-info/WHEEL
migas-0.4.0.dist-info/licenses/LICENSE
migas-0.4.0.dist-info/RECORD
