Metadata-Version: 2.1
Name: migas
Version: 0.4.0
Summary: A Python package to communicate with a migas server.
Project-URL: Bug Tracker, https://github.com/nipreps/migas-py/issues
Project-URL: Source Code, https://github.com/nipreps/migas-py
Author-email: The NiPreps Developers <nipreps@gmail.com>
License:                                  Apache License
License-File: LICENSE
Classifier: Development Status :: 3 - Alpha
Classifier: Intended Audience :: Developers
Classifier: Intended Audience :: Science/Research
Classifier: License :: OSI Approved :: Apache Software License
Classifier: Programming Language :: Python :: 3.8
Classifier: Programming Language :: Python :: 3.9
Classifier: Programming Language :: Python :: 3.10
Classifier: Programming Language :: Python :: 3.11
Classifier: Programming Language :: Python :: 3.12
Classifier: Topic :: Software Development :: Bug Tracking
Classifier: Topic :: System :: Networking :: Monitoring
Requires-Python: >=3.8
Requires-Dist: ci-info
Provides-Extra: dev
Requires-Dist: black; extra == 'dev'
Requires-Dist: isort; extra == 'dev'
Requires-Dist: pre-commit; extra == 'dev'
Provides-Extra: test
Requires-Dist: looseversion; extra == 'test'
Requires-Dist: pytest; extra == 'test'
Requires-Dist: requests; extra == 'test'
